{
  "symbol": "SPANK",
  "address": "0x42d6622deCe394b54999Fbd73D108123806f6a18",
  "decimals": 18,
  "name": "SpankChain",
  "ens_address": "spankchain.eth",
  "website": "https://spankchain.com",
  "logo": {
    "src": "https://raw.githubusercontent.com/TrustWallet/tokens/master/images/0x42d6622dece394b54999fbd73d108123806f6a18.png",
    "width": "",
    "height": "",
    "ipfs_hash": "",
    "origin": "http://trivial.co/static/vendor/icons/svg/color/spank.svg"
  },
  "support": {
    "email": "",
    "url": ""
  },
  "social": {
    "blog": "https://medium.com/spankchain",
    "chat": "",
    "facebook": "https://web.facebook.com/spankchain/",
    "forum": "",
    "github": "https://github.com/spankchain",
    "gitter": "",
    "instagram": "https://www.instagram.com/_spankchain",
    "linkedin": "",
    "reddit": "https://www.reddit.com/r/SpankChain",
    "discord": "https://discord.gg/WEsDaWZ",
    "telegram": "https://t.me/spankchain",
    "twitter": "https://twitter.com/SpankChain",
    "youtube": "https://www.youtube.com/channel/UCRonD1SJuucnq9GJCJL_crQ"
  }
}