{
  "symbol": "DRPU",
  "address": "0xe30e02f049957e2A5907589e06Ba646fB2c321bA",
  "decimals": 8,
  "name": "DRP Utility",
  "ens_address": "",
  "website": "https://www.dcorp.it/",
  "logo": {
    "src": "https://raw.githubusercontent.com/TrustWallet/tokens/master/images/0xe30e02f049957e2a5907589e06ba646fb2c321ba.png",
    "width": "",
    "height": "",
    "ipfs_hash": "",
    "sources": {
      "twitter": "http://pbs.twimg.com/profile_images/863664231048241154/428iXy0w.jpg",
      "trustwallet": "https://raw.githubusercontent.com/TrustWallet/tokens/master/images/0xe30e02f049957e2a5907589e06ba646fb2c321ba.png"
    },
    "sourceBest": "twitter",
    "origin": "http://pbs.twimg.com/profile_images/863664231048241154/428iXy0w.jpg"
  },
  "support": {
    "email": "info@dcorp.it",
    "url": ""
  },
  "social": {
    "blog": "",
    "chat": "",
    "facebook": "https://www.facebook.com/DCORP-1929877313957912/",
    "forum": "",
    "github": "",
    "gitter": "",
    "instagram": "",
    "linkedin": "https://www.linkedin.com/in/frank-bonnet-3b890865/",
    "reddit": "https://www.reddit.com/r/dcorp/",
    "slack": "",
    "telegram": "",
    "twitter": "https://twitter.com/DcorpVC",
    "youtube": ""
  }
}